unyt/__init__.py
unyt/_array_functions.py
unyt/_deprecation.py
unyt/_on_demand_imports.py
unyt/_parsing.py
unyt/_physical_ratios.py
unyt/_pint_conversions.py
unyt/_unit_lookup_table.py
unyt/_version.py
unyt/array.py
unyt/dask_array.py
unyt/dimensions.py
unyt/equivalencies.py
unyt/exceptions.py
unyt/mpl_interface.py
unyt/physical_constants.py
unyt/testing.py
unyt/unit_object.py
unyt/unit_registry.py
unyt/unit_symbols.py
unyt/unit_systems.py
unyt/_mpl_array_converter/__init__.py
unyt/tests/__init__.py
unyt/tests/test_array_functions.py
unyt/tests/test_dask_arrays.py
unyt/tests/test_define_unit.py
unyt/tests/test_mpl_interface.py
unyt/tests/test_no_duplicates.py
unyt/tests/test_unit_registry.py
unyt/tests/test_unit_systems.py
unyt/tests/test_units.py
unyt/tests/test_unyt_array.py
unyt/tests/test_unyt_testing.py
unyt/tests/data/__init__.py
unyt/tests/data/old_json_registry.txt
unyt-3.0.3.dist-info/LICENSE
unyt-3.0.3.dist-info/METADATA
unyt-3.0.3.dist-info/WHEEL
unyt-3.0.3.dist-info/top_level.txt
unyt-3.0.3.dist-info/RECORD
