Metadata-Version: 2.1
Name: unyt
Version: 3.0.3
Summary: A package for handling numpy arrays with units
Author-email: The yt project <yt-dev@python.org>
License: BSD-3-Clause
Project-URL: Homepage, https://github.com/yt-project/unyt
Project-URL: Documentation, https://unyt.readthedocs.io/en/stable/index.html
Project-URL: Changelog, https://unyt.readthedocs.io/en/stable/history.html
Keywords: unyt
Classifier: Development Status :: 5 - Production/Stable
Classifier: Intended Audience :: Developers
Classifier: License :: OSI Approved :: BSD License
Classifier: Natural Language :: English
Classifier: Programming Language :: Python :: 3
Classifier: Programming Language :: Python :: Implementation :: CPython
Requires-Python: >=3.9
License-File: LICENSE
Requires-Dist: numpy<3.0,>=1.19.3
Requires-Dist: sympy>=1.7
Requires-Dist: packaging>=20.9
